stix_shifter_modules/paloalto/__init__.py
stix_shifter_modules/paloalto/entry_point.py
stix_shifter_modules/paloalto/configuration/config.json
stix_shifter_modules/paloalto/configuration/dialects.json
stix_shifter_modules/paloalto/configuration/lang_en.json
stix_shifter_modules/paloalto/stix_translation/__init__.py
stix_shifter_modules/paloalto/stix_translation/json_to_stix_translator.py
stix_shifter_modules/paloalto/stix_translation/query_constructor.py
stix_shifter_modules/paloalto/stix_translation/query_translator.py
stix_shifter_modules/paloalto/stix_translation/transformers.py
stix_shifter_modules/paloalto/stix_translation/json/config_map.json
stix_shifter_modules/paloalto/stix_translation/json/fields_map.json
stix_shifter_modules/paloalto/stix_translation/json/operators.json
stix_shifter_modules/paloalto/stix_translation/json/to_stix_map.json
stix_shifter_modules/paloalto/stix_translation/json/xdr_data_from_stix_map.json
stix_shifter_modules/paloalto/stix_translation/json/stix_2_1/to_stix_map.json
stix_shifter_modules/paloalto/stix_translation/json/stix_2_1/xdr_data_from_stix_map.json
stix_shifter_modules/paloalto/stix_transmission/__init__.py
stix_shifter_modules/paloalto/stix_transmission/api_client.py
stix_shifter_modules/paloalto/stix_transmission/delete_connector.py
stix_shifter_modules/paloalto/stix_transmission/error_mapper.py
stix_shifter_modules/paloalto/stix_transmission/ping_connector.py
stix_shifter_modules/paloalto/stix_transmission/query_connector.py
stix_shifter_modules/paloalto/stix_transmission/response_mapper.py
stix_shifter_modules/paloalto/stix_transmission/results_connector.py
stix_shifter_modules/paloalto/stix_transmission/status_connector.py
stix_shifter_modules_paloalto-8.0.2.dist-info/licenses/AUTHORS.md
stix_shifter_modules_paloalto-8.0.2.dist-info/licenses/LICENSE.md
stix_shifter_modules_paloalto-8.0.2.dist-info/licenses/NOTICE
stix_shifter_modules_paloalto-8.0.2.dist-info/METADATA
stix_shifter_modules_paloalto-8.0.2.dist-info/WHEEL
stix_shifter_modules_paloalto-8.0.2.dist-info/top_level.txt
stix_shifter_modules_paloalto-8.0.2.dist-info/RECORD
